env_settings/__init__.py
env_settings/config.py
env_settings/generator.py
env_settings/utils.py
env_settings-1.0.3.dist-info/licenses/LICENSE
env_settings-1.0.3.dist-info/METADATA
env_settings-1.0.3.dist-info/WHEEL
env_settings-1.0.3.dist-info/top_level.txt
env_settings-1.0.3.dist-info/RECORD
