Metadata-Version: 2.4
Name: env-settings
Version: 1.0.3
Summary: Universal module for using Python program settings based on environment variables
Home-page: https://github.com/andy-kovalev/env-settings
Download-URL: https://github.com/andy-kovalev/env-settings.git
Author: Andy Kovalev
Author-email: kovalev.andy@yandex.ru
License: MIT License
Keywords: environment,variables,settings,env-settings
Classifier: Programming Language :: Python :: 3.11
Classifier: Operating System :: OS Independent
Requires-Python: >=3.9
License-File: LICENSE
Requires-Dist: python-dotenv
Dynamic: download-url
Dynamic: license-file
